{"cameraMode":{"drawMode":0,"name":"Shaded","section":"Shading Mode"},"sceneLighting":true,"audioPlay":false,"sceneViewState":{"showFog":true,"showMaterialUpdate":false,"showSkybox":true,"showFlares":true,"showImageEffects":true,"showParticleSystems":true},"in2DMode":false,"pivot":{"x":-0.2734975814819336,"y":2.35032320022583,"z":-5.866770267486572},"rotation":{"x":0.14589153230190278,"y":0.6985929012298584,"z":-0.14889976382255555,"w":0.6844797134399414},"size":17.023353576660158,"orthographic":false}