{"cameraMode":{"drawMode":0,"name":"Shaded","section":"Shading Mode"},"sceneLighting":true,"audioPlay":false,"sceneViewState":{"showFog":true,"showMaterialUpdate":false,"showSkybox":true,"showFlares":true,"showImageEffects":true,"showParticleSystems":true},"in2DMode":false,"pivot":{"x":2.9872360229492189,"y":2.2395172119140627,"z":26.83511734008789},"rotation":{"x":-0.12858015298843385,"y":0.4243749976158142,"z":-0.06102026626467705,"w":-0.8942313194274902},"size":127.99809265136719,"orthographic":false}